ddrfactlib.py
ddrlib.py
ddrparserlib.py
genie_parsers.py
ddr_python-1.0.16.dist-info/METADATA
ddr_python-1.0.16.dist-info/WHEEL
ddr_python-1.0.16.dist-info/top_level.txt
ddr_python-1.0.16.dist-info/RECORD
