Metadata-Version: 2.1
Name: ddr-python
Version: 1.0.16
Summary: Distributed Device Reasoning (DDR) IOS-XE runtime
Home-page: https://wwwin-github.cisco.com/petervh/ddr-python
Author: Peter Van Horne
Author-email: petervh@cisco.com
Classifier: Programming Language :: Python :: 3
Classifier: License :: OSI Approved :: MIT License
Classifier: Operating System :: OS Independent
Requires-Python: >=3.6
